README.rst
setup.py
rio_clip.egg-info/PKG-INFO
rio_clip.egg-info/SOURCES.txt
rio_clip.egg-info/dependency_links.txt
rio_clip.egg-info/entry_points.txt
rio_clip.egg-info/not-zip-safe
rio_clip.egg-info/requires.txt
rio_clip.egg-info/top_level.txt
rioclip/__init__.py
rioclip/scripts/__init__.py
rioclip/scripts/cli.py