Metadata-Version: 1.0
Name: rio-clip
Version: 0.0.2
Summary: Clip a geo-aware raster to the bounds of another.
Home-page: https://github.com/kapadia/rio-clip
Author: Amit Kapadia
Author-email: akapad@gmail.com
License: MIT
Platform: UNKNOWN
